django_dynamic_forms-0.5.3.dist-info/DESCRIPTION.rst
django_dynamic_forms-0.5.3.dist-info/LICENSE.txt
django_dynamic_forms-0.5.3.dist-info/METADATA
django_dynamic_forms-0.5.3.dist-info/RECORD
django_dynamic_forms-0.5.3.dist-info/WHEEL
django_dynamic_forms-0.5.3.dist-info/metadata.json
django_dynamic_forms-0.5.3.dist-info/top_level.txt
dynamic_forms/__init__.py
dynamic_forms/actions.py
dynamic_forms/admin.py
dynamic_forms/apps.py
dynamic_forms/conf.py
dynamic_forms/fields.py
dynamic_forms/formfields.py
dynamic_forms/forms.py
dynamic_forms/middlewares.py
dynamic_forms/models.py
dynamic_forms/urls.py
dynamic_forms/utils.py
dynamic_forms/views.py
dynamic_forms/contrib/__init__.py
dynamic_forms/contrib/simple_captcha/__init__.py
dynamic_forms/contrib/simple_captcha/models.py
dynamic_forms/locale/de/LC_MESSAGES/django.mo
dynamic_forms/locale/de/LC_MESSAGES/django.po
dynamic_forms/locale/en/LC_MESSAGES/django.mo
dynamic_forms/locale/en/LC_MESSAGES/django.po
dynamic_forms/locale/pt_BR/LC_MESSAGES/django.mo
dynamic_forms/locale/pt_BR/LC_MESSAGES/django.po
dynamic_forms/migrations/0001_initial.py
dynamic_forms/migrations/0002_auto_20140124_1844.py
dynamic_forms/migrations/0003_auto_20140916_1433.py
dynamic_forms/migrations/0004_formmodel_recipient_email.py
dynamic_forms/migrations/0005_auto_increase_form_label_max_length_255.py
dynamic_forms/migrations/__init__.py
dynamic_forms/templates/dynamic_forms/data_set.html
dynamic_forms/templates/dynamic_forms/data_set_404.html
dynamic_forms/templates/dynamic_forms/email.txt
dynamic_forms/templates/dynamic_forms/form.html
dynamic_forms/templates/dynamic_forms/form_success.html
